{
  "title": "Geroi in the Far North: The Battle Begins on August 17th ",
  "description": "A historical war drama set in the northern Kuril islands in the summer of 1945, where, even though the Pacific War has already ended, a Japanese tank regiment is suddenly confronted with an unexpected battle.",
  "artist": "Kakizaki Masasumi",
  "author": "Kakizaki Masasumi",
  "cover": "https://cdn.imgchest.com/files/457014e8f236.png",
  "chapters": {
    "1": {
      "title": "End of the War",
      "volume": "1",
      "last_updated": "1748288753",
      "groups": {
        "Year Zero": "/proxy/api/imgchest/chapter/m9yxnln3p7q"
      }
    },
    "2": {
      "title": "Shumshu",
      "volume": "1",
      "last_updated": "1750023990",
      "groups": {
        "Year Zero": "/proxy/api/imgchest/chapter/5xy2omoqz4l"
      }
    },
    "3": {
      "title": "Harsh Winter",
      "volume": "1",
      "last_updated": "1752871544",
      "groups": {
        "Year Zero": "/proxy/api/imgchest/chapter/xny8686e24b"
      }
    },
    "4": {
      "title": "Late Spring",
      "volume": "1",
      "last_updated": "1754268453",
      "groups": {
        "Year Zero": "/proxy/api/imgchest/chapter/ne7b6o6lmy5"
      }
    },
    "5": {
      "title": "Paramushir",
      "volume": "2",
      "last_updated": "1756422958",
      "groups": {
        "Year Zero": "/proxy/api/imgchest/chapter/o24a26qa27l"
      }
    },
    "6": {
      "title": "Bombing",
      "volume": "2",
      "last_updated": "1758983650",
      "groups": {
        "Year Zero": "/proxy/api/imgchest/chapter/dl7panekp7o"
      }
    },
    "7": {
      "title": "Family",
      "volume": "2",
      "last_updated": "1761074229",
      "groups": {
        "Year Zero": "/proxy/api/imgchest/chapter/wl7lawg3qyx"
      }
    },
    "8": {
      "title": "Secret Meeting",
      "volume": "2",
      "last_updated": "1767038191",
      "groups": {
        "Year Zero": "/proxy/api/imgchest/chapter/wl7lwda634x"
      }
    }
  }
}