{
  "title": "Nikaidou Hell Golf",
  "description": "Nikaidou Susumu, 35, has been unsuccessful in the professional test for 10 consecutive years, despite receiving support from his club. What awaits him in the future, as he is unable to give up the title of professional golfer, is either heaven or hell...",
  "artist": "Nobuyuki Fukumoto",
  "author": "Nobuyuki Fukumoto",
  "cover": "https://i.imgur.com/l3udtfO.jpeg",
  "chapters": {
    "1": {
      "title": "One's Dearest Wish",
      "volume": "1",
      "last_updated": "1758215278",
      "groups": {
        "FKMTKrazy": "/proxy/api/imgur/chapter/nikaidou1-zw8lZo7"
      }
    },
    "2": {
      "title": "Gloom",
      "volume": "1",
      "last_updated": "1758215501",
      "groups": {
        "FKMTKrazy": "/proxy/api/imgur/chapter/nikaidou2-J7i5bE0"
      }
    }
  }
}