{
  "title": "Nikaidou Hell Golf",
  "description": "Nikaidou Susumu, 35, has been unsuccessful in the professional test for 10 consecutive years, despite receiving support from his club. What awaits him in the future, as he is unable to give up the title of professional golfer, is either heaven or hell...",
  "artist": "Nobuyuki Fukumoto",
  "author": "Nobuyuki Fukumoto",
  "cover": "https://i.imgur.com/l3udtfO.jpeg",
  "chapters": {
    "1": {
      "title": "One's Dearest Wish",
      "volume": "1",
      "last_updated": "1758215278",
      "groups": {
        "FKMTKrazy": "/proxy/api/imgchest/chapter/qe4gmqm5j4j"
      }
    },
    "2": {
      "title": "Gloom",
      "volume": "1",
      "last_updated": "1758215501",
      "groups": {
        "FKMTKrazy": "/proxy/api/imgchest/chapter/a8463o35o4x"
      }
    },
    "3": {
      "title": "Consensus",
      "volume": "1",
      "last_updated": "1758215732",
      "groups": {
        "FKMTKrazy": "/proxy/api/imgchest/chapter/m9yx9n98qyq"
      }
    },
    "4": {
      "title": "Courage",
      "volume": "1",
      "last_updated": "1758216023",
      "groups": {
        "FKMTKrazy": "/proxy/api/imgchest/chapter/9p4nvzvjmyn"
      }
    },
    "5": {
      "title": "Reality",
      "volume": "1",
      "last_updated": "1758216136",
      "groups": {
        "FKMTKrazy": "/proxy/api/imgchest/chapter/6eyrana5x4p"
      }
    },
    "6": {
      "title": "One's Own Strength",
      "volume": "1",
      "last_updated": "1758280187",
      "groups": {
        "FKMTKrazy": "/proxy/api/imgchest/chapter/xny8e6e22yb"
      }
    },
    "7": {
      "title": "Witnessing",
      "volume": "1",
      "last_updated": "1758216509",
      "groups": {
        "FKMTKrazy": "/proxy/api/imgchest/chapter/na7kakavb48"
      }
    },
    "8": {
      "title": "Heaven's Net",
      "volume": "1",
      "last_updated": "1758216745",
      "groups": {
        "FKMTKrazy": "/proxy/api/imgchest/chapter/vj4jemegx78"
      }
    },
    "9": {
      "title": "Fraud",
      "volume": "1",
      "last_updated": "1758217051",
      "groups": {
        "FKMTKrazy": "/proxy/api/imgbox/chapter/aLINSTMIH6"
      }
    },
    "10": {
      "title": "Gap",
      "volume": "2",
      "last_updated": "1758217162",
      "groups": {
        "FKMTKrazy": "/proxy/api/imgchest/chapter/9rydq2qra4k"
      }
    },
    "11": {
      "title": "Lethargy",
      "volume": "2",
      "last_updated": "1758217309",
      "groups": {
        "FKMTKrazy": "/proxy/api/imgchest/chapter/lqyedldmm7d"
      }
    },
    "12": {
      "title": "Preservation",
      "volume": "2",
      "last_updated": "1758217434",
      "groups": {
        "FKMTKrazy": "/proxy/api/imgchest/chapter/bp45momqny5"
      }
    },
    "13": {
      "title": "Crux",
      "volume": "2",
      "last_updated": "1758280210",
      "groups": {
        "FKMTKrazy": "/proxy/api/imgchest/chapter/o24a262nd7l"
      }
    },
    "14": {
      "title": "Master",
      "volume": "2",
      "last_updated": "1758217573",
      "groups": {
        "FKMTKrazy": "/proxy/api/imgchest/chapter/92492k23byn"
      }
    },
    "15": {
      "title": "Kirishima",
      "volume": "2",
      "last_updated": "1758217618",
      "groups": {
        "FKMTKrazy": "/proxy/api/imgchest/chapter/ne7bl6lqmy5"
      }
    },
    "16": {
      "title": "Transform",
      "volume": "2",
      "last_updated": "1758217754",
      "groups": {
        "FKMTKrazy": "/proxy/api/imgchest/chapter/m9yx9n9dpyq"
      }
    },
    "17": {
      "title": "Duty",
      "volume": "2",
      "last_updated": "1758217865",
      "groups": {
        "FKMTKrazy": "/proxy/api/imgchest/chapter/5xy2qoqqzyl"
      }
    },
    "18": {
      "title": "Growing Older",
      "volume": "2",
      "last_updated": "1758218021",
      "groups": {
        "FKMTKrazy": "/proxy/api/imgchest/chapter/qb4z5p5ll4j"
      }
    },
    "19": {
      "title": "Graduation",
      "volume": "2",
      "last_updated": "1758218174",
      "groups": {
        "FKMTKrazy": "/proxy/api/imgchest/chapter/o24a262de7l"
      }
    },
    "20": {
      "title": "Loss",
      "volume": "2",
      "last_updated": "1758218209",
      "groups": {
        "FKMTKrazy": "/proxy/api/imgchest/chapter/ljyqakaad72"
      }
    },
    "21": {
      "title": "Reunion",
      "volume": "3",
      "last_updated": "1758218301",
      "groups": {
        "FKMTKrazy": "/proxy/api/imgchest/chapter/9rydq2qqa4k"
      }
    },
    "22": {
      "title": "Vocation",
      "volume": "3",
      "last_updated": "1758218322",
      "groups": {
        "FKMTKrazy": "/proxy/api/imgchest/chapter/ej7maeaa97d"
      }
    },
    "23": {
      "title": "Happiness",
      "volume": "3",
      "last_updated": "1758280226",
      "groups": {
        "FKMTKrazy": "/proxy/api/imgchest/chapter/qb4z5p5554j"
      }
    },
    "24": {
      "title": "Visitors",
      "volume": "3",
      "last_updated": "1758218804",
      "groups": {
        "FKMTKrazy": "/proxy/api/imgchest/chapter/a8463o33z4x"
      }
    },
    "25": {
      "title": "Confession",
      "volume": "3",
      "last_updated": "1758219370",
      "groups": {
        "FKMTKrazy": "/proxy/api/imgchest/chapter/m9yx9n99pyq"
      }
    },
    "26": {
      "title": "Turbulence",
      "volume": "3",
      "last_updated": "1758219445",
      "groups": {
        "FKMTKrazy": "/proxy/api/imgchest/chapter/92492k22byn"
      }
    },
    "27": {
      "title": "The Point",
      "volume": "3",
      "last_updated": "1758219659",
      "groups": {
        "FKMTKrazy": "/proxy/api/imgchest/chapter/ne7bl6llmy5"
      }
    },
    "28": {
      "title": "Fate",
      "volume": "3",
      "last_updated": "1758219738",
      "groups": {
        "FKMTKrazy": "/proxy/api/imgchest/chapter/dl7panaa37o"
      }
    },
    "29": {
      "title": "Hopes",
      "volume": "3",
      "last_updated": "1758219776",
      "groups": {
        "FKMTKrazy": "/proxy/api/imgchest/chapter/m9yx9n9q6yq"
      }
    },
    "30": {
      "title": "Stroke",
      "volume": "3",
      "last_updated": "1758219894",
      "groups": {
        "FKMTKrazy": "/proxy/api/imgchest/chapter/na7kakaa348"
      }
    },
    "31": {
      "title": "Activation",
      "volume": "4",
      "last_updated": "1758280241",
      "groups": {
        "FKMTKrazy": "/proxy/api/imgchest/chapter/wl7lawawxyx"
      }
    },
    "32": {
      "title": "Verification",
      "volume": "4",
      "last_updated": "1758220039",
      "groups": {
        "FKMTKrazy": "/proxy/api/imgchest/chapter/9rydq2q2a4k"
      }
    },
    "33": {
      "title": "Belief",
      "volume": "4",
      "last_updated": "1758280253",
      "groups": {
        "FKMTKrazy": "/proxy/api/imgchest/chapter/vj4jeme6978"
      }
    },
    "34": {
      "title": "Conflict",
      "volume": "4",
      "last_updated": "1758220115",
      "groups": {
        "FKMTKrazy": "/proxy/api/imgchest/chapter/ej7maea6a7d"
      }
    },
    "35": {
      "title": "Self-Esteem",
      "volume": "4",
      "last_updated": "1758220180",
      "groups": {
        "FKMTKrazy": "/proxy/api/imgchest/chapter/n87w9n9jqyx"
      }
    },
    "36": {
      "title": "Magic",
      "volume": "4",
      "last_updated": "1758220243",
      "groups": {
        "FKMTKrazy": "/proxy/api/imgchest/chapter/xny8e6e9wyb"
      }
    },
    "37": {
      "title": "Senior",
      "volume": "4",
      "last_updated": "1758220312",
      "groups": {
        "FKMTKrazy": "/proxy/api/imgchest/chapter/pg73dodogyr"
      }
    },
    "38": {
      "title": "Beacon",
      "volume": "4",
      "last_updated": "1758220366",
      "groups": {
        "FKMTKrazy": "/proxy/api/imgchest/chapter/n87w9n9nxyx"
      }
    },
    "39": {
      "title": "Respect",
      "volume": "4",
      "last_updated": "1758220414",
      "groups": {
        "FKMTKrazy": "/proxy/api/imgchest/chapter/bp45momony5"
      }
    },
    "40": {
      "title": "Legendary Player",
      "volume": "5",
      "last_updated": "1758220458",
      "groups": {
        "FKMTKrazy": "/proxy/api/imgbox/chapter/WVS4D7XG1I"
      }
    },
    "41": {
      "title": "Caution",
      "volume": "5",
      "last_updated": "1758280266",
      "groups": {
        "FKMTKrazy": "/proxy/api/imgchest/chapter/9p4nvzvzbyn"
      }
    },
    "42": {
      "title": "Practice",
      "volume": "5",
      "last_updated": "1758220778",
      "groups": {
        "FKMTKrazy": "/proxy/api/imgchest/chapter/md7oabab2yp"
      }
    },
    "43": {
      "title": "Small Person",
      "volume": "5",
      "last_updated": "1758220886",
      "groups": {
        "FKMTKrazy": "/proxy/api/imgchest/chapter/9p4nvzv65yn"
      }
    },
    "44": {
      "title": "Imp",
      "volume": "5",
      "last_updated": "1758220991",
      "groups": {
        "FKMTKrazy": "/proxy/api/imgchest/chapter/5xy2qoqx3yl"
      }
    },
    "45": {
      "title": "Boy",
      "volume": "5",
      "last_updated": "1758221041",
      "groups": {
        "FKMTKrazy": "/proxy/api/imgchest/chapter/wl7lawa5xyx"
      }
    },
    "46": {
      "title": "Radiant",
      "volume": "5",
      "last_updated": "1759001832",
      "groups": {
        "FKMTKrazy": "/proxy/api/imgchest/chapter/vj4jemen378"
      }
    },
    "47": {
      "title": "Temptation",
      "volume": "5",
      "last_updated": "1766652814",
      "groups": {
        "FKMTKrazy": "/proxy/api/imgchest/chapter/md7obvbr94p"
      }
    }
  }
}